esmcol_validator/__init__.py
esmcol_validator/cli.py
esmcol_validator/validator.py
esmcol_validator-2020.1.29.dist-info/LICENSE
esmcol_validator-2020.1.29.dist-info/METADATA
esmcol_validator-2020.1.29.dist-info/WHEEL
esmcol_validator-2020.1.29.dist-info/entry_points.txt
esmcol_validator-2020.1.29.dist-info/top_level.txt
esmcol_validator-2020.1.29.dist-info/RECORD
