Metadata-Version: 2.1
Name: esmcol-validator
Version: 2020.1.29
Summary: A package to validate ESM Collection files
Home-page: https://github.com/NCAR/esmcol-validator
Maintainer: Anderson Banihirwe
Maintainer-email: abanihi@ucar.edu
License: Apache 2.0
Keywords: intake,esm,catalog
Platform: UNKNOWN
Classifier: Development Status :: 4 - Beta
Classifier: License :: OSI Approved :: Apache Software License
Classifier: Operating System :: OS Independent
Classifier: Intended Audience :: Science/Research
Classifier: Programming Language :: Python
Classifier: Programming Language :: Python :: 3
Classifier: Programming Language :: Python :: 3.6
Classifier: Programming Language :: Python :: 3.7
Classifier: Topic :: Scientific/Engineering
Requires-Python: >=3.6
Requires-Dist: requests (>=2.19.1)
Requires-Dist: jsonschema (>=3.0.1)
Requires-Dist: click
Requires-Dist: pandas
